{
  "id": 99,
  "name": "npc_dota_hero_bristleback",
  "order_id": 99,
  "name_loc": "Bristleback",
  "bio_loc": "Ригварл никогда не уходил от драк и не поворачивался спиной к противнику, даже если тот был крупнее и сильнее его. Окрещённый пьяными толпами как Bristleback, он стал постоянным участником подпольных боев, что проводились в тавернах на тракте между Сломом и Эльзе. Однажды умелого бойца заприметил один трактирщик, искавший вышибалу в бар. За скромную выпивку он стал собирать с посетителей плату, следить за порядком и время от времени ломать конечности особо несговорчивым клиентам (а одному членистоногому бедняге однажды сломал целых пять). Но все же Ригварлу довелось встретить бойца, равного себе.\r\n\t\t\t\t<br><br>Однажды во время очередной вечерней вахты, уже будучи навеселе от хмеля, он подошёл за платой к одному кряжистому детине с севера и заплетающимся языком пробормотал: «Что-то не нравятся мне ваши бивни, уважаемый». Что тут началось! Это было побоище века! В бой бросилось с дюжину посетителей. Не уцелел ни один стул. Хотя Ригварл изрядно приложился к буянам, но и сам в полной мере схлопотал по печени. И все бы ничего, но случилось нечто страшное — клиент ушёл, не заплатив за выпивку. За несколько недель раны вышибалы затянулись, а вырванные иглы отросли, но удар по чести был нанесён непростительный. Счёт он оплатил из своего кармана, поклявшись выследить северянина и взыскать плату по полной. После этого он занялся тренировками, чего не делал никогда ранее, и неожиданно для себя сделал поразительное открытие. Расправив иглы и усмехнувшись сквозь зубы, он понял — иногда все же стоит показывать противнику спину.",
  "hype_loc": "В сражении Bristleback совсем не против подставить врагам спину. <b>Уменьшая весь урон</b>, который ему наносят сзади и сбоку, он безрассудно бросается в бой и обдаёт врагов <b>смертоносными иглами</b> и <b>замедляющими соплями</b>.",
  "npe_desc_loc": "Получает меньше урона, отвернувшись от врагов",
  "facets": [
    {
      "color": 2,
      "title_loc": "Snot Rocket",
      "description_loc": "Когда героя бьют в спину, он выпускает не иглы, а сопли от Viscous Nasal Goo. Кроме того, усиливает эффект соплей.",
      "name": "bristleback_snot_rocket",
      "icon": "snot",
      "gradient_id": 0,
      "index": 1
    },
    {
      "color": 0,
      "title_loc": "Seeing Red",
      "description_loc": "Герой может активировать способность Warpath, чтобы получить различные бонусы. В этом состоянии он не получает обзор от союзников.",
      "name": "bristleback_seeing_red",
      "icon": "no_vision",
      "gradient_id": 0,
      "index": 2
    }
  ],
  "str_base": 22,
  "str_gain": 2.7,
  "agi_base": 17,
  "agi_gain": 1.8,
  "int_base": 14,
  "int_gain": 2.8,
  "primary_attr": 0,
  "complexity": 1,
  "attack_capability": 1,
  "role_levels": [
    2,
    0,
    1,
    0,
    0,
    3,
    0,
    0,
    1
  ],
  "damage_min": 53,
  "damage_max": 59,
  "attack_rate": 1.8,
  "attack_range": 150,
  "projectile_speed": 900,
  "armor": 3.8333335,
  "magic_resistance": 25,
  "movement_speed": 295,
  "turn_rate": 0.9,
  "sight_range_day": 1800,
  "sight_range_night": 800,
  "max_health": 604,
  "health_regen": 3.2,
  "max_mana": 243,
  "mana_regen": 1.1,
  "abilities": [
    {
      "id": 5548,
      "name": "bristleback_viscous_nasal_goo",
      "name_loc": "Viscous Nasal Goo",
      "desc_loc": "Обильно сморкается на жертву, снижая её броню и скорость передвижения на %goo_duration% сек. Эффекты способности складываются, а время действия обновляется с каждым её применением.",
      "lore_loc": "Простуду, подхваченную в снегах, Ригварл делает своим преимуществом.",
      "notes_loc": [],
      "shard_loc": "",
      "scepter_loc": "",
      "facets_loc": [
        "",
        "Максимум эффектов и снижение брони за эффект увеличены.",
        ""
      ],
      "type": 0,
      "behavior": "134217736",
      "target_team": 2,
      "target_type": 19,
      "flags": 0,
      "damage": 0,
      "immunity": 4,
      "dispellable": 2,
      "max_level": 4,
      "cast_ranges": [
        650
      ],
      "cast_points": [
        0.3
      ],
      "channel_times": [
        0
      ],
      "cooldowns": [
        1.75
      ],
      "durations": [
        0
      ],
      "damages": [
        0,
        0,
        0,
        0
      ],
      "mana_costs": [
        12,
        16,
        20,
        24
      ],
      "gold_costs": [],
      "health_costs": [],
      "special_values": [
        {
          "name": "goo_speed",
          "values_float": [
            1000
          ],
          "is_percentage": false,
          "heading_loc": "",
          "bonuses": [],
          "values_shard": [],
          "values_scepter": [],
          "facet_bonus": {
            "name": "",
            "values": [],
            "operation": 0
          },
          "required_facet": ""
        },
        {
          "name": "goo_duration",
          "values_float": [
            5
          ],
          "is_percentage": false,
          "heading_loc": "",
          "bonuses": [],
          "values_shard": [],
          "values_scepter": [],
          "facet_bonus": {
            "name": "",
            "values": [],
            "operation": 0
          },
          "required_facet": ""
        },
        {
          "name": "base_armor",
          "values_float": [
            1.5,
            2,
            2.5,
            3
          ],
          "is_percentage": false,
          "heading_loc": "БАЗОВОЕ СНИЖЕНИЕ БРОНИ:",
          "bonuses": [],
          "values_shard": [],
          "values_scepter": [],
          "facet_bonus": {
            "name": "",
            "values": [],
            "operation": 0
          },
          "required_facet": ""
        },
        {
          "name": "armor_per_stack",
          "values_float": [
            1.5,
            2,
            2.5,
            3
          ],
          "is_percentage": false,
          "heading_loc": "СНИЖЕНИЕ БРОНИ ЗА ЭФФЕКТ:",
          "bonuses": [],
          "values_shard": [],
          "values_scepter": [],
          "facet_bonus": {
            "name": "bristleback_snot_rocket",
            "values": [
              0.5
            ],
            "operation": 0
          },
          "required_facet": ""
        },
        {
          "name": "base_move_slow",
          "values_float": [
            10
          ],
          "is_percentage": true,
          "heading_loc": "БАЗОВОЕ ЗАМЕДЛЕНИЕ ПЕРЕДВИЖЕНИЯ:",
          "bonuses": [],
          "values_shard": [],
          "values_scepter": [],
          "facet_bonus": {
            "name": "",
            "values": [],
            "operation": 0
          },
          "required_facet": ""
        },
        {
          "name": "move_slow_per_stack",
          "values_float": [
            3,
            6,
            9,
            12
          ],
          "is_percentage": true,
          "heading_loc": "ЗАМЕДЛЕНИЕ ЗА ЭФФЕКТ:",
          "bonuses": [],
          "values_shard": [],
          "values_scepter": [],
          "facet_bonus": {
            "name": "",
            "values": [],
            "operation": 0
          },
          "required_facet": ""
        },
        {
          "name": "stack_limit",
          "values_float": [
            4
          ],
          "is_percentage": false,
          "heading_loc": "МАКСИМУМ ЭФФЕКТОВ:",
          "bonuses": [],
          "values_shard": [],
          "values_scepter": [],
          "facet_bonus": {
            "name": "bristleback_snot_rocket",
            "values": [
              2
            ],
            "operation": 0
          },
          "required_facet": ""
        },
        {
          "name": "goo_duration_creep",
          "values_float": [
            10
          ],
          "is_percentage": false,
          "heading_loc": "",
          "bonuses": [],
          "values_shard": [],
          "values_scepter": [],
          "facet_bonus": {
            "name": "",
            "values": [],
            "operation": 0
          },
          "required_facet": ""
        },
        {
          "name": "AbilityCastRange",
          "values_float": [
            650
          ],
          "is_percentage": false,
          "heading_loc": "",
          "bonuses": [
            {
              "name": "special_bonus_unique_bristleback_5",
              "value": 250,
              "operation": 0
            }
          ],
          "values_shard": [],
          "values_scepter": [],
          "facet_bonus": {
            "name": "",
            "values": [],
            "operation": 0
          },
          "required_facet": ""
        },
        {
          "name": "AbilityCastPoint",
          "values_float": [
            0.3
          ],
          "is_percentage": false,
          "heading_loc": "",
          "bonuses": [],
          "values_shard": [],
          "values_scepter": [],
          "facet_bonus": {
            "name": "",
            "values": [],
            "operation": 0
          },
          "required_facet": ""
        },
        {
          "name": "AbilityManaCost",
          "values_float": [
            12,
            16,
            20,
            24
          ],
          "is_percentage": false,
          "heading_loc": "",
          "bonuses": [],
          "values_shard": [],
          "values_scepter": [],
          "facet_bonus": {
            "name": "",
            "values": [],
            "operation": 0
          },
          "required_facet": ""
        },
        {
          "name": "AbilityCooldown",
          "values_float": [
            1.75
          ],
          "is_percentage": false,
          "heading_loc": "",
          "bonuses": [],
          "values_shard": [],
          "values_scepter": [],
          "facet_bonus": {
            "name": "",
            "values": [],
            "operation": 0
          },
          "required_facet": ""
        }
      ],
      "is_item": false,
      "ability_has_scepter": false,
      "ability_has_shard": false,
      "ability_is_granted_by_scepter": false,
      "ability_is_granted_by_shard": false,
      "ability_is_innate": false,
      "item_cost": 0,
      "item_initial_charges": 0,
      "item_neutral_tier": 4294967295,
      "item_stock_max": 0,
      "item_stock_time": 0,
      "item_quality": 0
    },
    {
      "id": 5549,
      "name": "bristleback_quill_spray",
      "name_loc": "Quill Spray",
      "desc_loc": "Выпускает во все стороны иглы, нанося урон всем врагам вокруг себя. Жертвы получают дополнительный урон за каждое попадание иглами за последние %quill_stack_duration% сек.",
      "lore_loc": "Честь вышибалы — острый вопрос. Как и его шипы.",
      "notes_loc": [
        "Урон от этой способности не уменьшается способностями, блокирующими урон."
      ],
      "shard_loc": "",
      "scepter_loc": "",
      "facets_loc": [
        "",
        "",
        ""
      ],
      "type": 0,
      "behavior": "6148",
      "target_team": 0,
      "target_type": 0,
      "flags": 0,
      "damage": 1,
      "immunity": 3,
      "dispellable": 3,
      "max_level": 4,
      "cast_ranges": [
        0
      ],
      "cast_points": [
        0,
        0,
        0,
        0
      ],
      "channel_times": [
        0
      ],
      "cooldowns": [
        3,
        3,
        3,
        3
      ],
      "durations": [
        0
      ],
      "damages": [
        0,
        0,
        0,
        0
      ],
      "mana_costs": [
        35,
        35,
        35,
        35
      ],
      "gold_costs": [],
      "health_costs": [],
      "special_values": [
        {
          "name": "radius",
          "values_float": [
            700
          ],
          "is_percentage": false,
          "heading_loc": "РАДИУС:",
          "bonuses": [],
          "values_shard": [],
          "values_scepter": [],
          "facet_bonus": {
            "name": "",
            "values": [],
            "operation": 0
          },
          "required_facet": ""
        },
        {
          "name": "quill_base_damage",
          "values_float": [
            25,
            45,
            65,
            85
          ],
          "is_percentage": false,
          "heading_loc": "БАЗОВЫЙ УРОН:",
          "bonuses": [],
          "values_shard": [],
          "values_scepter": [],
          "facet_bonus": {
            "name": "",
            "values": [],
            "operation": 0
          },
          "required_facet": ""
        },
        {
          "name": "quill_stack_damage",
          "values_float": [
            30
          ],
          "is_percentage": false,
          "heading_loc": "ДОПОЛНИТЕЛЬНЫЙ УРОН:",
          "bonuses": [
            {
              "name": "special_bonus_unique_bristleback_2",
              "value": 20,
              "operation": 0
            }
          ],
          "values_shard": [],
          "values_scepter": [],
          "facet_bonus": {
            "name": "",
            "values": [],
            "operation": 0
          },
          "required_facet": ""
        },
        {
          "name": "quill_stack_duration",
          "values_float": [
            14
          ],
          "is_percentage": false,
          "heading_loc": "ДЛИТЕЛЬНОСТЬ ОДНОГО ЭФФЕКТА:",
          "bonuses": [],
          "values_shard": [],
          "values_scepter": [],
          "facet_bonus": {
            "name": "",
            "values": [],
            "operation": 0
          },
          "required_facet": ""
        },
        {
          "name": "max_damage",
          "values_float": [
            500
          ],
          "is_percentage": false,
          "heading_loc": "МАКСИМАЛЬНЫЙ УРОН:",
          "bonuses": [],
          "values_shard": [],
          "values_scepter": [],
          "facet_bonus": {
            "name": "",
            "values": [],
            "operation": 0
          },
          "required_facet": ""
        },
        {
          "name": "projectile_speed",
          "values_float": [
            2400
          ],
          "is_percentage": false,
          "heading_loc": "",
          "bonuses": [],
          "values_shard": [],
          "values_scepter": [],
          "facet_bonus": {
            "name": "",
            "values": [],
            "operation": 0
          },
          "required_facet": ""
        },
        {
          "name": "AbilityManaCost",
          "values_float": [
            35
          ],
          "is_percentage": false,
          "heading_loc": "",
          "bonuses": [],
          "values_shard": [],
          "values_scepter": [],
          "facet_bonus": {
            "name": "",
            "values": [],
            "operation": 0
          },
          "required_facet": ""
        },
        {
          "name": "AbilityCooldown",
          "values_float": [
            3
          ],
          "is_percentage": false,
          "heading_loc": "",
          "bonuses": [],
          "values_shard": [],
          "values_scepter": [],
          "facet_bonus": {
            "name": "",
            "values": [],
            "operation": 0
          },
          "required_facet": ""
        }
      ],
      "is_item": false,
      "ability_has_scepter": false,
      "ability_has_shard": false,
      "ability_is_granted_by_scepter": false,
      "ability_is_granted_by_shard": false,
      "ability_is_innate": false,
      "item_cost": 0,
      "item_initial_charges": 0,
      "item_neutral_tier": 4294967295,
      "item_stock_max": 0,
      "item_stock_time": 0,
      "item_quality": 0
    },
    {
      "id": 5550,
      "name": "bristleback_bristleback",
      "name_loc": "Bristleback",
      "desc_loc": "Герой получает меньше урона от атак со спины и с боков. При получении %quill_release_threshold% урона со спины применяется способность Quill Spray текущего уровня.",
      "lore_loc": "Иногда бывает полезно повернуться спиной к врагу во время битвы.",
      "notes_loc": [
        "Спиной героя считаются 70 градусов от середины его спины.",
        "Боками героя считаются 110 градусов от середины его спины."
      ],
      "shard_loc": "",
      "scepter_loc": "Позволяет применить эту способность на точку. Герой разворачивается к ней спиной и спустя %activation_delay% сек. выпускает %activation_num_quill_sprays% волн игл от Quill Spray в конусовидной области. Под действием этой способности герой замедлен на %activation_movement_speed_pct%%% и не может поворачиваться и атаковать, но может применять заклинания в любом направлении. Интервал волн: %activation_spray_interval% сек.",
      "facets_loc": [
        "",
        "Вместо игл герой выпускает во всех врагов неподалёку сопли от способности Viscous Nasal Goo текущего уровня.",
        ""
      ],
      "type": 0,
      "behavior": "2",
      "target_team": 0,
      "target_type": 0,
      "flags": 0,
      "damage": 0,
      "immunity": 0,
      "dispellable": 0,
      "max_level": 4,
      "cast_ranges": [
        0
      ],
      "cast_points": [
        0
      ],
      "channel_times": [
        0
      ],
      "cooldowns": [
        0
      ],
      "durations": [
        0
      ],
      "damages": [
        0,
        0,
        0,
        0
      ],
      "mana_costs": [
        0
      ],
      "gold_costs": [],
      "health_costs": [],
      "special_values": [
        {
          "name": "side_damage_reduction",
          "values_float": [
            8,
            12,
            16,
            20
          ],
          "is_percentage": true,
          "heading_loc": "СНИЖЕНИЕ УРОНА ОТ АТАК С БОКОВ:",
          "bonuses": [
            {
              "name": "special_bonus_unique_bristleback_6",
              "value": 4,
              "operation": 0
            }
          ],
          "values_shard": [],
          "values_scepter": [],
          "facet_bonus": {
            "name": "",
            "values": [],
            "operation": 0
          },
          "required_facet": ""
        },
        {
          "name": "back_damage_reduction",
          "values_float": [
            16,
            24,
            32,
            40
          ],
          "is_percentage": true,
          "heading_loc": "СНИЖЕНИЕ УРОНА ОТ АТАК В СПИНУ:",
          "bonuses": [
            {
              "name": "special_bonus_unique_bristleback_6",
              "value": 8,
              "operation": 0
            }
          ],
          "values_shard": [],
          "values_scepter": [],
          "facet_bonus": {
            "name": "",
            "values": [],
            "operation": 0
          },
          "required_facet": ""
        },
        {
          "name": "side_angle",
          "values_float": [
            110
          ],
          "is_percentage": false,
          "heading_loc": "",
          "bonuses": [],
          "values_shard": [],
          "values_scepter": [],
          "facet_bonus": {
            "name": "",
            "values": [],
            "operation": 0
          },
          "required_facet": ""
        },
        {
          "name": "back_angle",
          "values_float": [
            70
          ],
          "is_percentage": false,
          "heading_loc": "",
          "bonuses": [],
          "values_shard": [],
          "values_scepter": [],
          "facet_bonus": {
            "name": "",
            "values": [],
            "operation": 0
          },
          "required_facet": ""
        },
        {
          "name": "quill_release_threshold",
          "values_float": [
            275,
            250,
            225,
            200
          ],
          "is_percentage": false,
          "heading_loc": "ПОРОГ УРОНА:",
          "bonuses": [],
          "values_shard": [],
          "values_scepter": [],
          "facet_bonus": {
            "name": "",
            "values": [],
            "operation": 0
          },
          "required_facet": ""
        },
        {
          "name": "quill_release_interval",
          "values_float": [
            0.1
          ],
          "is_percentage": false,
          "heading_loc": "",
          "bonuses": [],
          "values_shard": [],
          "values_scepter": [],
          "facet_bonus": {
            "name": "",
            "values": [],
            "operation": 0
          },
          "required_facet": ""
        },
        {
          "name": "goo_radius",
          "values_float": [
            0
          ],
          "is_percentage": false,
          "heading_loc": "РАДИУС РАЗБРЫЗГИВАНИЯ СОПЛЕЙ:",
          "bonuses": [],
          "values_shard": [],
          "values_scepter": [],
          "facet_bonus": {
            "name": "bristleback_snot_rocket",
            "values": [
              750
            ],
            "operation": 0
          },
          "required_facet": "bristleback_snot_rocket"
        },
        {
          "name": "activation_cooldown",
          "values_float": [
            24
          ],
          "is_percentage": false,
          "heading_loc": "",
          "bonuses": [],
          "values_shard": [],
          "values_scepter": [],
          "facet_bonus": {
            "name": "",
            "values": [],
            "operation": 0
          },
          "required_facet": ""
        },
        {
          "name": "activation_manacost",
          "values_float": [
            125
          ],
          "is_percentage": false,
          "heading_loc": "",
          "bonuses": [],
          "values_shard": [],
          "values_scepter": [],
          "facet_bonus": {
            "name": "",
            "values": [],
            "operation": 0
          },
          "required_facet": ""
        },
        {
          "name": "activation_delay",
          "values_float": [
            0.5
          ],
          "is_percentage": false,
          "heading_loc": "",
          "bonuses": [],
          "values_shard": [],
          "values_scepter": [],
          "facet_bonus": {
            "name": "",
            "values": [],
            "operation": 0
          },
          "required_facet": ""
        },
        {
          "name": "activation_num_quill_sprays",
          "values_float": [
            5
          ],
          "is_percentage": false,
          "heading_loc": "",
          "bonuses": [],
          "values_shard": [],
          "values_scepter": [],
          "facet_bonus": {
            "name": "",
            "values": [],
            "operation": 0
          },
          "required_facet": ""
        },
        {
          "name": "activation_spray_interval",
          "values_float": [
            0.4
          ],
          "is_percentage": false,
          "heading_loc": "",
          "bonuses": [],
          "values_shard": [],
          "values_scepter": [],
          "facet_bonus": {
            "name": "",
            "values": [],
            "operation": 0
          },
          "required_facet": ""
        },
        {
          "name": "activation_angle",
          "values_float": [
            45
          ],
          "is_percentage": false,
          "heading_loc": "",
          "bonuses": [],
          "values_shard": [],
          "values_scepter": [],
          "facet_bonus": {
            "name": "",
            "values": [],
            "operation": 0
          },
          "required_facet": ""
        },
        {
          "name": "activation_movement_speed_pct",
          "values_float": [
            -40
          ],
          "is_percentage": false,
          "heading_loc": "",
          "bonuses": [],
          "values_shard": [],
          "values_scepter": [],
          "facet_bonus": {
            "name": "",
            "values": [],
            "operation": 0
          },
          "required_facet": ""
        },
        {
          "name": "activation_turn_rate_pct",
          "values_float": [
            -100
          ],
          "is_percentage": false,
          "heading_loc": "",
          "bonuses": [],
          "values_shard": [],
          "values_scepter": [],
          "facet_bonus": {
            "name": "",
            "values": [],
            "operation": 0
          },
          "required_facet": ""
        },
        {
          "name": "activation_disable_turning",
          "values_float": [
            1
          ],
          "is_percentage": false,
          "heading_loc": "",
          "bonuses": [],
          "values_shard": [],
          "values_scepter": [],
          "facet_bonus": {
            "name": "",
            "values": [],
            "operation": 0
          },
          "required_facet": ""
        },
        {
          "name": "activation_ignore_cast_angle",
          "values_float": [
            1
          ],
          "is_percentage": false,
          "heading_loc": "",
          "bonuses": [],
          "values_shard": [],
          "values_scepter": [],
          "facet_bonus": {
            "name": "",
            "values": [],
            "operation": 0
          },
          "required_facet": ""
        },
        {
          "name": "activation_turn_rate",
          "values_float": [
            500
          ],
          "is_percentage": false,
          "heading_loc": "",
          "bonuses": [],
          "values_shard": [],
          "values_scepter": [],
          "facet_bonus": {
            "name": "",
            "values": [],
            "operation": 0
          },
          "required_facet": ""
        }
      ],
      "is_item": false,
      "ability_has_scepter": true,
      "ability_has_shard": false,
      "ability_is_granted_by_scepter": false,
      "ability_is_granted_by_shard": false,
      "ability_is_innate": false,
      "item_cost": 0,
      "item_initial_charges": 0,
      "item_neutral_tier": 4294967295,
      "item_stock_max": 0,
      "item_stock_time": 0,
      "item_quality": 0
    },
    {
      "id": 643,
      "name": "bristleback_hairball",
      "name_loc": "Hairball",
      "desc_loc": "Отхаркивает в указанную область комок игл. Приземлившись, он лопается и применяет на всех врагов вокруг несколько эффектов Viscous Nasal Goo и один эффект Quill Spray.",
      "lore_loc": "Иглогрив использует в качестве оружия все части своего тела — даже те, которые случайно проглотил.",
      "notes_loc": [],
      "shard_loc": "",
      "scepter_loc": "",
      "facets_loc": [
        "",
        "",
        ""
      ],
      "type": 0,
      "behavior": "8589934641",
      "target_team": 2,
      "target_type": 19,
      "flags": 0,
      "damage": 0,
      "immunity": 1,
      "dispellable": 2,
      "max_level": 1,
      "cast_ranges": [
        750
      ],
      "cast_points": [
        0.1
      ],
      "channel_times": [
        0
      ],
      "cooldowns": [
        13
      ],
      "durations": [
        0
      ],
      "damages": [
        0,
        0,
        0,
        0
      ],
      "mana_costs": [
        60
      ],
      "gold_costs": [],
      "health_costs": [],
      "special_values": [
        {
          "name": "projectile_speed",
          "values_float": [
            1200
          ],
          "is_percentage": false,
          "heading_loc": "",
          "bonuses": [],
          "values_shard": [],
          "values_scepter": [],
          "facet_bonus": {
            "name": "",
            "values": [],
            "operation": 0
          },
          "required_facet": ""
        },
        {
          "name": "radius",
          "values_float": [
            700
          ],
          "is_percentage": false,
          "heading_loc": "РАДИУС:",
          "bonuses": [],
          "values_shard": [],
          "values_scepter": [],
          "facet_bonus": {
            "name": "",
            "values": [],
            "operation": 0
          },
          "required_facet": ""
        },
        {
          "name": "quill_stacks",
          "values_float": [
            1
          ],
          "is_percentage": false,
          "heading_loc": "ЧИСЛО ЭФФЕКТОВ QUILL SPRAY:",
          "bonuses": [],
          "values_shard": [],
          "values_scepter": [],
          "facet_bonus": {
            "name": "",
            "values": [],
            "operation": 0
          },
          "required_facet": ""
        },
        {
          "name": "goo_stacks",
          "values_float": [
            2
          ],
          "is_percentage": false,
          "heading_loc": "ЧИСЛО ЭФФЕКТОВ VISCOUS NASAL GOO:",
          "bonuses": [],
          "values_shard": [],
          "values_scepter": [],
          "facet_bonus": {
            "name": "",
            "values": [],
            "operation": 0
          },
          "required_facet": ""
        },
        {
          "name": "AbilityCastRange",
          "values_float": [
            750
          ],
          "is_percentage": false,
          "heading_loc": "",
          "bonuses": [],
          "values_shard": [],
          "values_scepter": [],
          "facet_bonus": {
            "name": "",
            "values": [],
            "operation": 0
          },
          "required_facet": ""
        },
        {
          "name": "AbilityCastPoint",
          "values_float": [
            0.1
          ],
          "is_percentage": false,
          "heading_loc": "",
          "bonuses": [],
          "values_shard": [],
          "values_scepter": [],
          "facet_bonus": {
            "name": "",
            "values": [],
            "operation": 0
          },
          "required_facet": ""
        },
        {
          "name": "AbilityManaCost",
          "values_float": [
            60
          ],
          "is_percentage": false,
          "heading_loc": "",
          "bonuses": [],
          "values_shard": [],
          "values_scepter": [],
          "facet_bonus": {
            "name": "",
            "values": [],
            "operation": 0
          },
          "required_facet": ""
        },
        {
          "name": "AbilityCooldown",
          "values_float": [
            13
          ],
          "is_percentage": false,
          "heading_loc": "",
          "bonuses": [],
          "values_shard": [],
          "values_scepter": [],
          "facet_bonus": {
            "name": "",
            "values": [],
            "operation": 0
          },
          "required_facet": ""
        }
      ],
      "is_item": false,
      "ability_has_scepter": false,
      "ability_has_shard": false,
      "ability_is_granted_by_scepter": false,
      "ability_is_granted_by_shard": true,
      "ability_is_innate": false,
      "item_cost": 0,
      "item_initial_charges": 0,
      "item_neutral_tier": 4294967295,
      "item_stock_max": 0,
      "item_stock_time": 0,
      "item_quality": 0
    },
    {
      "id": 5551,
      "name": "bristleback_warpath",
      "name_loc": "Warpath",
      "desc_loc": "Герой нагоняет на себя ярость каждый раз, когда использует способность, повышая свои скорость передвижения и урон.",
      "lore_loc": "«Держи себя в руках», — часто наставляла его мама. Но в битве ярость всегда к месту.",
      "notes_loc": [
        "Бонусы передаются иллюзиям героя.",
        "Не срабатывает от использования предметов.",
        "Получение эффектов отключается истощением.",
        "Существующие эффекты не отключаются истощением."
      ],
      "shard_loc": "",
      "scepter_loc": "",
      "facets_loc": [
        "Эффекты Warpath увеличивают не урон, а скорость атаки.",
        "",
        "Способность можно активировать, чтобы ненадолго получить бонус к скорости передвижения и урону от атак. В этом состоянии герой видит только в узком конусе перед собой и не получает обзор от союзников."
      ],
      "type": 1,
      "behavior": "2",
      "target_team": 0,
      "target_type": 0,
      "flags": 0,
      "damage": 0,
      "immunity": 0,
      "dispellable": 3,
      "max_level": 3,
      "cast_ranges": [
        0
      ],
      "cast_points": [
        0
      ],
      "channel_times": [
        0
      ],
      "cooldowns": [
        45
      ],
      "durations": [
        10,
        10,
        10
      ],
      "damages": [
        0,
        0,
        0,
        0
      ],
      "mana_costs": [
        0
      ],
      "gold_costs": [],
      "health_costs": [],
      "special_values": [
        {
          "name": "damage_per_stack",
          "values_float": [
            15,
            20,
            25
          ],
          "is_percentage": false,
          "heading_loc": "БОНУС К УРОНУ ЗА ЭФФЕКТ:",
          "bonuses": [
            {
              "name": "special_bonus_unique_bristleback_3",
              "value": 18,
              "operation": 0
            }
          ],
          "values_shard": [],
          "values_scepter": [],
          "facet_bonus": {
            "name": "bristleback_berserk",
            "values": [
              5
            ],
            "operation": 5
          },
          "required_facet": ""
        },
        {
          "name": "aspd_per_stack",
          "values_float": [
            0,
            0,
            0
          ],
          "is_percentage": false,
          "heading_loc": "",
          "bonuses": [],
          "values_shard": [],
          "values_scepter": [],
          "facet_bonus": {
            "name": "bristleback_berserk",
            "values": [
              10,
              15,
              20
            ],
            "operation": 5
          },
          "required_facet": "bristleback_berserk"
        },
        {
          "name": "move_speed_per_stack",
          "values_float": [
            2,
            2.5,
            3
          ],
          "is_percentage": true,
          "heading_loc": "БОНУС К СКОРОСТИ ЗА ЭФФЕКТ:",
          "bonuses": [],
          "values_shard": [],
          "values_scepter": [],
          "facet_bonus": {
            "name": "",
            "values": [],
            "operation": 0
          },
          "required_facet": ""
        },
        {
          "name": "stack_duration",
          "values_float": [
            16,
            18,
            20
          ],
          "is_percentage": false,
          "heading_loc": "ДЛИТЕЛЬНОСТЬ ОДНОГО ЭФФЕКТА:",
          "bonuses": [],
          "values_shard": [],
          "values_scepter": [],
          "facet_bonus": {
            "name": "",
            "values": [],
            "operation": 0
          },
          "required_facet": ""
        },
        {
          "name": "max_stacks",
          "values_float": [
            8,
            10,
            12
          ],
          "is_percentage": false,
          "heading_loc": "МАКС. ЭФФЕКТОВ:",
          "bonuses": [],
          "values_shard": [],
          "values_scepter": [],
          "facet_bonus": {
            "name": "",
            "values": [],
            "operation": 0
          },
          "required_facet": ""
        },
        {
          "name": "active_bonus_attack_percent",
          "values_float": [
            0
          ],
          "is_percentage": true,
          "heading_loc": "ДОП. УРОН ЗА ЭФФЕКТ ПРИ АКТИВАЦИИ:",
          "bonuses": [],
          "values_shard": [],
          "values_scepter": [],
          "facet_bonus": {
            "name": "bristleback_seeing_red",
            "values": [
              50
            ],
            "operation": 0
          },
          "required_facet": "bristleback_seeing_red"
        },
        {
          "name": "active_bonus_movement_percent",
          "values_float": [
            0
          ],
          "is_percentage": true,
          "heading_loc": "ДОП. СКОРОСТЬ ЗА ЭФФЕКТ ПРИ АКТИВАЦИИ:",
          "bonuses": [],
          "values_shard": [],
          "values_scepter": [],
          "facet_bonus": {
            "name": "bristleback_seeing_red",
            "values": [
              50
            ],
            "operation": 0
          },
          "required_facet": "bristleback_seeing_red"
        },
        {
          "name": "active_duration",
          "values_float": [
            0,
            0,
            0
          ],
          "is_percentage": false,
          "heading_loc": "ДЛИТЕЛЬНОСТЬ:",
          "bonuses": [],
          "values_shard": [],
          "values_scepter": [],
          "facet_bonus": {
            "name": "bristleback_seeing_red",
            "values": [
              4,
              5,
              6
            ],
            "operation": 0
          },
          "required_facet": "bristleback_seeing_red"
        },
        {
          "name": "active_view_angle_restriction",
          "values_float": [
            0
          ],
          "is_percentage": false,
          "heading_loc": "",
          "bonuses": [],
          "values_shard": [],
          "values_scepter": [],
          "facet_bonus": {
            "name": "bristleback_seeing_red",
            "values": [
              110
            ],
            "operation": 0
          },
          "required_facet": "bristleback_seeing_red"
        },
        {
          "name": "AbilityDuration",
          "values_float": [
            10
          ],
          "is_percentage": false,
          "heading_loc": "",
          "bonuses": [],
          "values_shard": [],
          "values_scepter": [],
          "facet_bonus": {
            "name": "",
            "values": [],
            "operation": 0
          },
          "required_facet": ""
        },
        {
          "name": "AbilityManaCost",
          "values_float": [
            0,
            0,
            0
          ],
          "is_percentage": false,
          "heading_loc": "",
          "bonuses": [],
          "values_shard": [],
          "values_scepter": [],
          "facet_bonus": {
            "name": "bristleback_seeing_red",
            "values": [
              55,
              65,
              75
            ],
            "operation": 0
          },
          "required_facet": "bristleback_seeing_red"
        },
        {
          "name": "AbilityCooldown",
          "values_float": [
            45
          ],
          "is_percentage": false,
          "heading_loc": "",
          "bonuses": [],
          "values_shard": [],
          "values_scepter": [],
          "facet_bonus": {
            "name": "",
            "values": [],
            "operation": 0
          },
          "required_facet": ""
        }
      ],
      "is_item": false,
      "ability_has_scepter": false,
      "ability_has_shard": false,
      "ability_is_granted_by_scepter": false,
      "ability_is_granted_by_shard": false,
      "ability_is_innate": false,
      "item_cost": 0,
      "item_initial_charges": 0,
      "item_neutral_tier": 4294967295,
      "item_stock_max": 0,
      "item_stock_time": 0,
      "item_quality": 0
    },
    {
      "id": 1479,
      "name": "bristleback_prickly",
      "name_loc": "Prickly",
      "desc_loc": "Герой наносит врагам позади на %amp_pct%%% больше урона, а его отрицательные эффекты действуют на них на %amp_pct%%% дольше.",
      "lore_loc": "",
      "notes_loc": [],
      "shard_loc": "",
      "scepter_loc": "",
      "facets_loc": [
        "",
        "",
        ""
      ],
      "type": 0,
      "behavior": "8796093022210",
      "target_team": 0,
      "target_type": 0,
      "flags": 0,
      "damage": 1,
      "immunity": 4,
      "dispellable": 2,
      "max_level": 1,
      "cast_ranges": [
        0
      ],
      "cast_points": [
        0
      ],
      "channel_times": [
        0
      ],
      "cooldowns": [
        0
      ],
      "durations": [
        0
      ],
      "damages": [
        0,
        0,
        0,
        0
      ],
      "mana_costs": [
        0
      ],
      "gold_costs": [],
      "health_costs": [],
      "special_values": [
        {
          "name": "amp_pct",
          "values_float": [
            10
          ],
          "is_percentage": false,
          "heading_loc": "",
          "bonuses": [],
          "values_shard": [],
          "values_scepter": [],
          "facet_bonus": {
            "name": "",
            "values": [],
            "operation": 0
          },
          "required_facet": ""
        },
        {
          "name": "angle",
          "values_float": [
            110
          ],
          "is_percentage": false,
          "heading_loc": "",
          "bonuses": [],
          "values_shard": [],
          "values_scepter": [],
          "facet_bonus": {
            "name": "",
            "values": [],
            "operation": 0
          },
          "required_facet": ""
        }
      ],
      "is_item": false,
      "ability_has_scepter": false,
      "ability_has_shard": false,
      "ability_is_granted_by_scepter": false,
      "ability_is_granted_by_shard": false,
      "ability_is_innate": true,
      "item_cost": 0,
      "item_initial_charges": 0,
      "item_neutral_tier": 4294967295,
      "item_stock_max": 0,
      "item_stock_time": 0,
      "item_quality": 0
    }
  ],
  "talents": [
    {
      "id": 6016,
      "name": "special_bonus_attack_speed_25",
      "name_loc": "+{s:value} к скорости атаки",
      "desc_loc": "",
      "lore_loc": "",
      "notes_loc": [],
      "shard_loc": "",
      "scepter_loc": "",
      "facets_loc": [
        "",
        "",
        ""
      ],
      "type": 2,
      "behavior": "2",
      "target_team": 0,
      "target_type": 0,
      "flags": 0,
      "damage": 0,
      "immunity": 0,
      "dispellable": 0,
      "max_level": 4,
      "cast_ranges": [
        0
      ],
      "cast_points": [
        0
      ],
      "channel_times": [
        0
      ],
      "cooldowns": [
        0
      ],
      "durations": [
        0
      ],
      "damages": [
        0,
        0,
        0,
        0
      ],
      "mana_costs": [
        0
      ],
      "gold_costs": [],
      "health_costs": [],
      "special_values": [
        {
          "name": "value",
          "values_float": [
            25
          ],
          "is_percentage": false,
          "heading_loc": "",
          "bonuses": [],
          "values_shard": [],
          "values_scepter": [],
          "facet_bonus": {
            "name": "",
            "values": [],
            "operation": 0
          },
          "required_facet": ""
        }
      ],
      "is_item": false,
      "ability_has_scepter": false,
      "ability_has_shard": false,
      "ability_is_granted_by_scepter": false,
      "ability_is_granted_by_shard": false,
      "ability_is_innate": false,
      "item_cost": 0,
      "item_initial_charges": 0,
      "item_neutral_tier": 4294967295,
      "item_stock_max": 0,
      "item_stock_time": 0,
      "item_quality": 0
    },
    {
      "id": 7132,
      "name": "special_bonus_mp_regen_150",
      "name_loc": "+{s:value} маны в секунду",
      "desc_loc": "",
      "lore_loc": "",
      "notes_loc": [],
      "shard_loc": "",
      "scepter_loc": "",
      "facets_loc": [
        "",
        "",
        ""
      ],
      "type": 2,
      "behavior": "2",
      "target_team": 0,
      "target_type": 0,
      "flags": 0,
      "damage": 0,
      "immunity": 0,
      "dispellable": 0,
      "max_level": 4,
      "cast_ranges": [
        0
      ],
      "cast_points": [
        0
      ],
      "channel_times": [
        0
      ],
      "cooldowns": [
        0
      ],
      "durations": [
        0
      ],
      "damages": [
        0,
        0,
        0,
        0
      ],
      "mana_costs": [
        0
      ],
      "gold_costs": [],
      "health_costs": [],
      "special_values": [
        {
          "name": "value",
          "values_float": [
            1.5
          ],
          "is_percentage": false,
          "heading_loc": "",
          "bonuses": [],
          "values_shard": [],
          "values_scepter": [],
          "facet_bonus": {
            "name": "",
            "values": [],
            "operation": 0
          },
          "required_facet": ""
        }
      ],
      "is_item": false,
      "ability_has_scepter": false,
      "ability_has_shard": false,
      "ability_is_granted_by_scepter": false,
      "ability_is_granted_by_shard": false,
      "ability_is_innate": false,
      "item_cost": 0,
      "item_initial_charges": 0,
      "item_neutral_tier": 4294967295,
      "item_stock_max": 0,
      "item_stock_time": 0,
      "item_quality": 0
    },
    {
      "id": 1078,
      "name": "special_bonus_unique_bristleback_5",
      "name_loc": "+{s:bonus_AbilityCastRange} к дальн. применения Viscous Nasal Goo",
      "desc_loc": "",
      "lore_loc": "",
      "notes_loc": [],
      "shard_loc": "",
      "scepter_loc": "",
      "facets_loc": [
        "",
        "",
        ""
      ],
      "type": 2,
      "behavior": "2",
      "target_team": 0,
      "target_type": 0,
      "flags": 0,
      "damage": 0,
      "immunity": 0,
      "dispellable": 0,
      "max_level": 4,
      "cast_ranges": [
        0
      ],
      "cast_points": [
        0
      ],
      "channel_times": [
        0
      ],
      "cooldowns": [
        0
      ],
      "durations": [
        0
      ],
      "damages": [
        0,
        0,
        0,
        0
      ],
      "mana_costs": [
        0
      ],
      "gold_costs": [],
      "health_costs": [],
      "special_values": [],
      "is_item": false,
      "ability_has_scepter": false,
      "ability_has_shard": false,
      "ability_is_granted_by_scepter": false,
      "ability_is_granted_by_shard": false,
      "ability_is_innate": false,
      "item_cost": 0,
      "item_initial_charges": 0,
      "item_neutral_tier": 4294967295,
      "item_stock_max": 0,
      "item_stock_time": 0,
      "item_quality": 0
    },
    {
      "id": 1079,
      "name": "special_bonus_unique_bristleback_6",
      "name_loc": "+{s:bonus_back_damage_reduction}%/{s:bonus_side_damage_reduction}% к снижению урона сзади/сбоку от Bristleback",
      "desc_loc": "",
      "lore_loc": "",
      "notes_loc": [],
      "shard_loc": "",
      "scepter_loc": "",
      "facets_loc": [
        "",
        "",
        ""
      ],
      "type": 2,
      "behavior": "2",
      "target_team": 0,
      "target_type": 0,
      "flags": 0,
      "damage": 0,
      "immunity": 0,
      "dispellable": 0,
      "max_level": 4,
      "cast_ranges": [
        0
      ],
      "cast_points": [
        0
      ],
      "channel_times": [
        0
      ],
      "cooldowns": [
        0
      ],
      "durations": [
        0
      ],
      "damages": [
        0,
        0,
        0,
        0
      ],
      "mana_costs": [
        0
      ],
      "gold_costs": [],
      "health_costs": [],
      "special_values": [],
      "is_item": false,
      "ability_has_scepter": false,
      "ability_has_shard": false,
      "ability_is_granted_by_scepter": false,
      "ability_is_granted_by_shard": false,
      "ability_is_innate": false,
      "item_cost": 0,
      "item_initial_charges": 0,
      "item_neutral_tier": 4294967295,
      "item_stock_max": 0,
      "item_stock_time": 0,
      "item_quality": 0
    },
    {
      "id": 6308,
      "name": "special_bonus_hp_regen_25",
      "name_loc": "+{s:value} здоровья в секунду",
      "desc_loc": "",
      "lore_loc": "",
      "notes_loc": [],
      "shard_loc": "",
      "scepter_loc": "",
      "facets_loc": [
        "",
        "",
        ""
      ],
      "type": 2,
      "behavior": "2",
      "target_team": 0,
      "target_type": 0,
      "flags": 0,
      "damage": 0,
      "immunity": 0,
      "dispellable": 0,
      "max_level": 4,
      "cast_ranges": [
        0
      ],
      "cast_points": [
        0
      ],
      "channel_times": [
        0
      ],
      "cooldowns": [
        0
      ],
      "durations": [
        0
      ],
      "damages": [
        0,
        0,
        0,
        0
      ],
      "mana_costs": [
        0
      ],
      "gold_costs": [],
      "health_costs": [],
      "special_values": [
        {
          "name": "value",
          "values_float": [
            25
          ],
          "is_percentage": false,
          "heading_loc": "",
          "bonuses": [],
          "values_shard": [],
          "values_scepter": [],
          "facet_bonus": {
            "name": "",
            "values": [],
            "operation": 0
          },
          "required_facet": ""
        }
      ],
      "is_item": false,
      "ability_has_scepter": false,
      "ability_has_shard": false,
      "ability_is_granted_by_scepter": false,
      "ability_is_granted_by_shard": false,
      "ability_is_innate": false,
      "item_cost": 0,
      "item_initial_charges": 0,
      "item_neutral_tier": 4294967295,
      "item_stock_max": 0,
      "item_stock_time": 0,
      "item_quality": 0
    },
    {
      "id": 6360,
      "name": "special_bonus_unique_bristleback_2",
      "name_loc": "+{s:bonus_quill_stack_damage} к дополнительному урону от Quill Spray",
      "desc_loc": "",
      "lore_loc": "",
      "notes_loc": [],
      "shard_loc": "",
      "scepter_loc": "",
      "facets_loc": [
        "",
        "",
        ""
      ],
      "type": 2,
      "behavior": "2",
      "target_team": 0,
      "target_type": 0,
      "flags": 0,
      "damage": 0,
      "immunity": 0,
      "dispellable": 0,
      "max_level": 4,
      "cast_ranges": [
        0
      ],
      "cast_points": [
        0
      ],
      "channel_times": [
        0
      ],
      "cooldowns": [
        0
      ],
      "durations": [
        0
      ],
      "damages": [
        0,
        0,
        0,
        0
      ],
      "mana_costs": [
        0
      ],
      "gold_costs": [],
      "health_costs": [],
      "special_values": [],
      "is_item": false,
      "ability_has_scepter": false,
      "ability_has_shard": false,
      "ability_is_granted_by_scepter": false,
      "ability_is_granted_by_shard": false,
      "ability_is_innate": false,
      "item_cost": 0,
      "item_initial_charges": 0,
      "item_neutral_tier": 4294967295,
      "item_stock_max": 0,
      "item_stock_time": 0,
      "item_quality": 0
    },
    {
      "id": 434,
      "name": "special_bonus_spell_lifesteal_12",
      "name_loc": "+{s:value}% к вампиризму заклинаниями",
      "desc_loc": "",
      "lore_loc": "",
      "notes_loc": [],
      "shard_loc": "",
      "scepter_loc": "",
      "facets_loc": [
        "",
        "",
        ""
      ],
      "type": 2,
      "behavior": "2",
      "target_team": 0,
      "target_type": 0,
      "flags": 0,
      "damage": 0,
      "immunity": 0,
      "dispellable": 0,
      "max_level": 4,
      "cast_ranges": [
        0
      ],
      "cast_points": [
        0
      ],
      "channel_times": [
        0
      ],
      "cooldowns": [
        0
      ],
      "durations": [
        0
      ],
      "damages": [
        0,
        0,
        0,
        0
      ],
      "mana_costs": [
        0
      ],
      "gold_costs": [],
      "health_costs": [],
      "special_values": [
        {
          "name": "value",
          "values_float": [
            12
          ],
          "is_percentage": false,
          "heading_loc": "",
          "bonuses": [],
          "values_shard": [],
          "values_scepter": [],
          "facet_bonus": {
            "name": "",
            "values": [],
            "operation": 0
          },
          "required_facet": ""
        }
      ],
      "is_item": false,
      "ability_has_scepter": false,
      "ability_has_shard": false,
      "ability_is_granted_by_scepter": false,
      "ability_is_granted_by_shard": false,
      "ability_is_innate": false,
      "item_cost": 0,
      "item_initial_charges": 0,
      "item_neutral_tier": 4294967295,
      "item_stock_max": 0,
      "item_stock_time": 0,
      "item_quality": 0
    },
    {
      "id": 6615,
      "name": "special_bonus_unique_bristleback_3",
      "name_loc": "+{s:bonus_damage_per_stack} к урону за эффект Warpath",
      "desc_loc": "",
      "lore_loc": "",
      "notes_loc": [],
      "shard_loc": "",
      "scepter_loc": "",
      "facets_loc": [
        "",
        "",
        ""
      ],
      "type": 2,
      "behavior": "2",
      "target_team": 0,
      "target_type": 0,
      "flags": 0,
      "damage": 0,
      "immunity": 0,
      "dispellable": 0,
      "max_level": 4,
      "cast_ranges": [
        0
      ],
      "cast_points": [
        0
      ],
      "channel_times": [
        0
      ],
      "cooldowns": [
        0
      ],
      "durations": [
        0
      ],
      "damages": [
        0,
        0,
        0,
        0
      ],
      "mana_costs": [
        0
      ],
      "gold_costs": [],
      "health_costs": [],
      "special_values": [],
      "is_item": false,
      "ability_has_scepter": false,
      "ability_has_shard": false,
      "ability_is_granted_by_scepter": false,
      "ability_is_granted_by_shard": false,
      "ability_is_innate": false,
      "item_cost": 0,
      "item_initial_charges": 0,
      "item_neutral_tier": 4294967295,
      "item_stock_max": 0,
      "item_stock_time": 0,
      "item_quality": 0
    }
  ],
  "facet_abilities": [
    {
      "abilities": []
    },
    {
      "abilities": []
    }
  ]
}