[
  {
    "id": 1119,
    "name": "clinkz_tar_bomb",
    "name_loc": "Tar Bomb",
    "desc_loc": "Герой бросает в указанного врага снаряд со смолой, который при попадании наносит магический урон и на %ground_duration% сек. разливает по земле смоляную лужу. Наступившие в неё противники замедляются и получают больше физического урона от атак владельца способности и скелетов-лучников.<br><br>Скелеты-лучники автоматически начинают атаковать врага, по которому попал снаряд этой способности. Если включено автоприменение, герой будет пытаться применить эту способность при атаке.",
    "lore_loc": "После битвы с Мараксиформом костяной лучник обнаружил на месте своего сердца подручный источник ихора.",
    "notes_loc": [],
    "shard_loc": "",
    "scepter_loc": "",
    "facets_loc": [],
    "type": 0,
    "behavior": "4136",
    "target_team": 2,
    "target_type": 23,
    "flags": 0,
    "damage": 1,
    "immunity": 0,
    "dispellable": 2,
    "max_level": 4,
    "cast_ranges": [
      1000
    ],
    "cast_points": [
      0.2,
      0.2,
      0.2,
      0.2
    ],
    "channel_times": [
      0
    ],
    "cooldowns": [
      7,
      6,
      5,
      4
    ],
    "durations": [
      0
    ],
    "damages": [
      0,
      0,
      0,
      0
    ],
    "mana_costs": [
      45,
      50,
      55,
      60
    ],
    "gold_costs": [],
    "health_costs": [],
    "special_values": [
      {
        "name": "radius",
        "values_float": [
          325
        ],
        "is_percentage": false,
        "heading_loc": "РАДИУС:",
        "bonuses": [],
        "values_shard": [],
        "values_scepter": [],
        "facet_bonus": {
          "name": "",
          "values": [],
          "operation": 0
        },
        "required_facet": ""
      },
      {
        "name": "projectile_speed",
        "values_float": [
          2000
        ],
        "is_percentage": false,
        "heading_loc": "",
        "bonuses": [],
        "values_shard": [],
        "values_scepter": [],
        "facet_bonus": {
          "name": "",
          "values": [],
          "operation": 0
        },
        "required_facet": ""
      },
      {
        "name": "damage_bonus",
        "values_float": [
          15,
          25,
          35,
          45
        ],
        "is_percentage": false,
        "heading_loc": "ДОП. УРОН:",
        "bonuses": [],
        "values_shard": [],
        "values_scepter": [],
        "facet_bonus": {
          "name": "",
          "values": [],
          "operation": 0
        },
        "required_facet": ""
      },
      {
        "name": "ground_duration",
        "values_float": [
          5
        ],
        "is_percentage": false,
        "heading_loc": "ДЛИТЕЛЬНОСТЬ ЛУЖИ:",
        "bonuses": [],
        "values_shard": [],
        "values_scepter": [],
        "facet_bonus": {
          "name": "",
          "values": [],
          "operation": 0
        },
        "required_facet": ""
      },
      {
        "name": "slow_movement_speed",
        "values_float": [
          -16,
          -19,
          -22,
          -25
        ],
        "is_percentage": true,
        "heading_loc": "ЗАМЕДЛЕНИЕ ПЕРЕДВИЖЕНИЯ:",
        "bonuses": [],
        "values_shard": [],
        "values_scepter": [],
        "facet_bonus": {
          "name": "",
          "values": [],
          "operation": 0
        },
        "required_facet": ""
      },
      {
        "name": "slow_duration",
        "values_float": [
          2.5
        ],
        "is_percentage": false,
        "heading_loc": "ДЛИТЕЛЬНОСТЬ ЗАМЕДЛЕНИЯ:",
        "bonuses": [],
        "values_shard": [],
        "values_scepter": [],
        "facet_bonus": {
          "name": "",
          "values": [],
          "operation": 0
        },
        "required_facet": ""
      },
      {
        "name": "has_multishot",
        "values_float": [],
        "is_percentage": false,
        "heading_loc": "",
        "bonuses": [
          {
            "name": "special_bonus_unique_clinkz_3",
            "value": 1,
            "operation": 0
          }
        ],
        "values_shard": [],
        "values_scepter": [],
        "facet_bonus": {
          "name": "",
          "values": [],
          "operation": 0
        },
        "required_facet": ""
      },
      {
        "name": "impact_damage",
        "values_float": [
          40,
          60,
          80,
          100
        ],
        "is_percentage": false,
        "heading_loc": "УРОН ОТ ПОПАДАНИЯ:",
        "bonuses": [],
        "values_shard": [],
        "values_scepter": [],
        "facet_bonus": {
          "name": "",
          "values": [],
          "operation": 0
        },
        "required_facet": ""
      },
      {
        "name": "AbilityCastRange",
        "values_float": [
          1000
        ],
        "is_percentage": false,
        "heading_loc": "",
        "bonuses": [],
        "values_shard": [],
        "values_scepter": [],
        "facet_bonus": {
          "name": "",
          "values": [],
          "operation": 0
        },
        "required_facet": ""
      },
      {
        "name": "AbilityCastPoint",
        "values_float": [
          0.2
        ],
        "is_percentage": false,
        "heading_loc": "",
        "bonuses": [],
        "values_shard": [],
        "values_scepter": [],
        "facet_bonus": {
          "name": "",
          "values": [],
          "operation": 0
        },
        "required_facet": ""
      },
      {
        "name": "AbilityManaCost",
        "values_float": [
          45,
          50,
          55,
          60
        ],
        "is_percentage": false,
        "heading_loc": "",
        "bonuses": [],
        "values_shard": [],
        "values_scepter": [],
        "facet_bonus": {
          "name": "",
          "values": [],
          "operation": 0
        },
        "required_facet": ""
      },
      {
        "name": "AbilityCooldown",
        "values_float": [
          7,
          6,
          5,
          4
        ],
        "is_percentage": false,
        "heading_loc": "",
        "bonuses": [],
        "values_shard": [],
        "values_scepter": [],
        "facet_bonus": {
          "name": "",
          "values": [],
          "operation": 0
        },
        "required_facet": ""
      }
    ],
    "is_item": false,
    "ability_has_scepter": false,
    "ability_has_shard": false,
    "ability_is_granted_by_scepter": false,
    "ability_is_granted_by_shard": false,
    "ability_is_innate": false,
    "item_cost": 0,
    "item_initial_charges": 0,
    "item_neutral_tier": 4294967295,
    "item_stock_max": 0,
    "item_stock_time": 0,
    "item_quality": 0
  }
]